medium_api/__init__.py
medium_api/_archived_articles.py
medium_api/_article.py
medium_api/_latestposts.py
medium_api/_medium_list.py
medium_api/_publication.py
medium_api/_recommended_feed.py
medium_api/_recommended_lists.py
medium_api/_recommended_users.py
medium_api/_top_writers.py
medium_api/_topfeeds.py
medium_api/_user.py
medium_api/medium.py
medium_api-0.6.1.dist-info/LICENSE
medium_api-0.6.1.dist-info/METADATA
medium_api-0.6.1.dist-info/WHEEL
medium_api-0.6.1.dist-info/top_level.txt
medium_api-0.6.1.dist-info/zip-safe
medium_api-0.6.1.dist-info/RECORD
