Metadata-Version: 2.1
Name: medium-api
Version: 0.6.1
Summary: Python Wrapper on top of Medium API to quickly extract data from https://medium.com.
Home-page: https://github.com/weeping-angel/medium-api
Author: Nishu Jain
Author-email: nishujain1997.19@gmail.com
License: MIT
Platform: unix
Platform: linux
Platform: osx
Platform: win32
Platform: cygwin
Classifier: Development Status :: 5 - Production/Stable
Classifier: Intended Audience :: Developers
Classifier: License :: OSI Approved :: MIT License
Classifier: Natural Language :: English
Classifier: Programming Language :: Python :: 3
Classifier: Programming Language :: Python :: 3 :: Only
Classifier: Programming Language :: Python :: 3.6
Classifier: Programming Language :: Python :: 3.7
Classifier: Programming Language :: Python :: 3.8
Classifier: Programming Language :: Python :: 3.9
Requires-Python: >=3.6
License-File: LICENSE
